Workbook

Sheet Variables
A1: Setting | B1: Value | C1: Notes
A2: Care home fee per week | B2: 2200 | C2: What the home charges (£/week)
A4: Cash savings at start | B4: 53000 | C4: £
A5: Home value at start | B5: 135000 | C5: £
A6: Alimony per year | B6: 25200 | C6: £/year (counted as income)
A7: Pension per year | B7: 6500 | C7: £/year (counted as income)
A8: Personal Expenses Allowance (PEA) | B8: 35.9 | C8: Weekly council subsidy
A9: Computed: weekly income | B9: =((B6+B7)/52)+B8
A10: Computed: annual income | B10: =SUM(B6:B7)+B8*52
A12: Free Personal Care (FPC) rate | B12: 260.3 | C12: Paid by council regardless of capital (£/week)
A13: Free Nursing Care (FNC) rate | B13: 117.1 | C13: Paid only if nursing care awarded (£/week)
A14: Nursing care awarded? | B14: No | C14: Yes = FNC paid + higher standard rate; No = personal-only
A16: Council standard rate - personal care only | B16: 930.45 | C16: NCHC rate without nursing (£/week)
A17: Council standard rate - with nursing | B17: 1074.13 | C17: NCHC rate including nursing care (£/week)
A18: Upper capital limit | B18: 36750 | C18: Above this: self-funder (£)
A19: Lower capital limit | B19: 22750 | C19: Below this: no tariff income (£)
A20: Tariff income per £250 | B20: 1 | C20: £ per week per £250 (or part) over lower limit
A21: Tariff band | B21: 250 | C21: £ of capital per tariff band
A22: Weeks until FPC/FNC awarded | B22: 10 | C22: Personal & nursing care awarded this many weeks after entry
A23: Care home accepts standard rate? | B23: Yes | C23: Yes = no top-up once council-funded; No = resident pays fee minus standard rate
A24: Date enters care home | B24: 46296 | C24: Used for the date column
A25: Weeks home value is disregarded | B25: 12 | C25: 12-week property disregard (0 = count immediately)
A26: Computed: effective standard rate | B26: =IF(B14="Yes",B17,B16) | C26: Standard rate with or without nursing
A27: Computed: top-up per week | B27: =IF(B23="Yes",0,B2-B26) | C27: Fee minus standard rate (0 if home accepts standard rate)
A28: Capital level triggering means-test review | B28: 60000 | C28: £ — council reviews finances here, ahead of taking over subsidy at the upper limit
A29: Chart duration (years) | B29: 5 | C29: Model & chart length. Change DURATION_YEARS in the script, then re-run to regenerate.
A30: Care home billing period (weeks, paid upfront) | B30: 4 | C30: Fees billed every N weeks, paid at the start of each period

Sheet Chart
A1: Key milestones (live — recalculated from the Variables sheet)
A3: Total weekly income | B3: =Variables!B9
A4: Effective council standard rate | B4: =Variables!B26
A5: Top-up per week (0 if home accepts standard rate) | B5: =Variables!B27
A6: Total wealth at start | B6: =Variables!B4+Variables!B5
A8: Week cash runs out -> home must be sold | B8: =IF(COUNTIF(Data!W2:W261,TRUE)=0,"Never",MATCH(TRUE,Data!W2:W261,0))
A9: Week total wealth falls to £60K (means-test review) | B9: =MATCH(TRUE,Data!Y2:Y261,0)
A10: Means-test crossing date (£60K) | B10: =TEXT(INDEX(Data!$B$2:$B$261,MATCH(TRUE,Data!$Y$2:$Y$261,0)),"dd mmm yyyy")
A11: Week council takes over funding (total wealth <= upper limit) | B11: =MATCH(TRUE,Data!Z2:Z261,0)
A12: Upper-threshold crossing date (£36,750) | B12: =TEXT(INDEX(Data!$B$2:$B$261,MATCH(TRUE,Data!$Z$2:$Z$261,0)),"dd mmm yyyy")
A13: Week total wealth first falls to lower limit | B13: =IF(COUNTIF(Data!V2:V261,TRUE)=0,"Never - capital stabilises",MATCH(TRUE,Data!V2:V261,0))
A14: Minimum total wealth reached | B14: =MIN(Data!AB2:AB261)
A15: Total wealth at end of 5 years | B15: =INDEX(Data!AB2:AB261,260)

Sheet Data
A1: Week | B1: Date | C1: Cash - start | D1: Home - start | E1: Assessed capital - start | F1: Total wealth - start | G1: FPC this week | H1: FNC this week | I1: Tariff income | J1: Assessed contribution | K1: Top-up | L1: Council pays | M1: Resident pays | N1: Net change | O1: Total wealth - end | P1: Cash - end | Q1: Home - end | R1: Phase | S1: Upper limit | T1: Lower limit | U1: Council contributing? | V1: Below lower limit? | W1: Cash exhausted? | X1: Means-test threshold | Y1: Below means-test threshold? | Z1: Total wealth <= upper limit? | AA1: Capital (assessment) - start | AB1: Capital (assessment) - end | AC1: Care home payment this week | AD1: Means-test crossing (£60K, 03 Aug 2028) | AE1: Upper crossing (£36,750, 07 Dec 2028)
A2: 1 | B2: =Variables!$B$24+(A2-1)*7 | C2: =Variables!$B$4 | D2: =Variables!$B$5 | E2: =C2+IF(A2>Variables!$B$25,D2,0) | F2: =C2+D2 | G2: =IF(A2>Variables!$B$22,Variables!$B$12,0) | H2: =IF(AND(A2>Variables!$B$22,Variables!$B$14="Yes"),Variables!$B$13,0) | I2: =IF(AA2>Variables!$B$18,0,IF(AA2>Variables!$B$19,CEILING((AA2-Variables!$B$19)/Variables!$B$21,1)*Variables!$B$20,0)) | J2: =IF(AA2<=Variables!$B$18,MIN(Variables!$B$9-Variables!$B$8+I2,Variables!$B$26),0) | K2: =IF(AA2<=Variables!$B$18,Variables!$B$27,0) | L2: =IF(AA2>Variables!$B$18,G2+H2,Variables!$B$26-J2) | M2: =IF(AA2>Variables!$B$18,Variables!$B$2-G2-H2,J2+K2) | N2: =Variables!$B$9-AC2 | O2: =F2+N2 | P2: =MAX(0,C2+N2) | Q2: =D2+MIN(0,C2+N2) | R2: =IF(AA2>Variables!$B$18,"Self-funder",IF(AA2>Variables!$B$19,"Tariff band - council contributing","Council pays standard rate")) | S2: =Variables!$B$18 | T2: =Variables!$B$19 | U2: =AA2<=Variables!$B$18 | V2: =AA2<=Variables!$B$19 | W2: =P2<=0 | X2: =Variables!$B$28 | Y2: =AB2<=Variables!$B$28 | Z2: =AB2<=Variables!$B$18 | AA2: =Variables!$B$4+Variables!$B$5 | AB2: =AA2+Variables!$B$9-M2 | AC2: =IF(MOD(A2-1,Variables!$B$30)=0,Variables!$B$30*M2,0) | AD2: =IF(A2=MATCH(TRUE,$Y$2:$Y$261,0),MAX($AB$2:$AB$261),IF(A2=MATCH(TRUE,$Y$2:$Y$261,0)-1,0,NA())) | AE2: =IF(A2=MATCH(TRUE,$Z$2:$Z$261,0),MAX($AB$2:$AB$261),IF(A2=MATCH(TRUE,$Z$2:$Z$261,0)-1,0,NA()))
A3: 2 | B3: =Variables!$B$24+(A3-1)*7 | C3: =P2 | D3: =Q2 | E3: =C3+IF(A3>Variables!$B$25,D3,0) | F3: =C3+D3 | G3: =IF(A3>Variables!$B$22,Variables!$B$12,0) | H3: =IF(AND(A3>Variables!$B$22,Variables!$B$14="Yes"),Variables!$B$13,0) | I3: =IF(AA3>Variables!$B$18,0,IF(AA3>Variables!$B$19,CEILING((AA3-Variables!$B$19)/Variables!$B$21,1)*Variables!$B$20,0)) | J3: =IF(AA3<=Variables!$B$18,MIN(Variables!$B$9-Variables!$B$8+I3,Variables!$B$26),0) | K3: =IF(AA3<=Variables!$B$18,Variables!$B$27,0) | L3: =IF(AA3>Variables!$B$18,G3+H3,Variables!$B$26-J3) | M3: =IF(AA3>Variables!$B$18,Variables!$B$2-G3-H3,J3+K3) | N3: =Variables!$B$9-AC3 | O3: =F3+N3 | P3: =MAX(0,C3+N3) | Q3: =D3+MIN(0,C3+N3) | R3: =IF(AA3>Variables!$B$18,"Self-funder",IF(AA3>Variables!$B$19,"Tariff band - council contributing","Council pays standard rate")) | S3: =Variables!$B$18 | T3: =Variables!$B$19 | U3: =AA3<=Variables!$B$18 | V3: =AA3<=Variables!$B$19 | W3: =P3<=0 | X3: =Variables!$B$28 | Y3: =AB3<=Variables!$B$28 | Z3: =AB3<=Variables!$B$18 | AA3: =AB2 | AB3: =AA3+Variables!$B$9-M3 | AC3: =IF(MOD(A3-1,Variables!$B$30)=0,Variables!$B$30*M3,0) | AD3: =IF(A3=MATCH(TRUE,$Y$2:$Y$261,0),MAX($AB$2:$AB$261),IF(A3=MATCH(TRUE,$Y$2:$Y$261,0)-1,0,NA())) | AE3: =IF(A3=MATCH(TRUE,$Z$2:$Z$261,0),MAX($AB$2:$AB$261),IF(A3=MATCH(TRUE,$Z$2:$Z$261,0)-1,0,NA()))
A4: 3 | B4: =Variables!$B$24+(A4-1)*7 | C4: =P3 | D4: =Q3 | E4: =C4+IF(A4>Variables!$B$25,D4,0) | F4: =C4+D4 | G4: =IF(A4>Variables!$B$22,Variables!$B$12,0) | H4: =IF(AND(A4>Variables!$B$22,Variables!$B$14="Yes"),Variables!$B$13,0) | I4: =IF(AA4>Variables!$B$18,0,IF(AA4>Variables!$B$19,CEILING((AA4-Variables!$B$19)/Variables!$B$21,1)*Variables!$B$20,0)) | J4: =IF(AA4<=Variables!$B$18,MIN(Variables!$B$9-Variables!$B$8+I4,Variables!$B$26),0) | K4: =IF(AA4<=Variables!$B$18,Variables!$B$27,0) | L4: =IF(AA4>Variables!$B$18,G4+H4,Variables!$B$26-J4) | M4: =IF(AA4>Variables!$B$18,Variables!$B$2-G4-H4,J4+K4) | N4: =Variables!$B$9-AC4 | O4: =F4+N4 | P4: =MAX(0,C4+N4) | Q4: =D4+MIN(0,C4+N4) | R4: =IF(AA4>Variables!$B$18,"Self-funder",IF(AA4>Variables!$B$19,"Tariff band - council contributing","Council pays standard rate")) | S4: =Variables!$B$18 | T4: =Variables!$B$19 | U4: =AA4<=Variables!$B$18 | V4: =AA4<=Variables!$B$19 | W4: =P4<=0 | X4: =Variables!$B$28 | Y4: =AB4<=Variables!$B$28 | Z4: =AB4<=Variables!$B$18 | AA4: =AB3 | AB4: =AA4+Variables!$B$9-M4 | AC4: =IF(MOD(A4-1,Variables!$B$30)=0,Variables!$B$30*M4,0) | AD4: =IF(A4=MATCH(TRUE,$Y$2:$Y$261,0),MAX($AB$2:$AB$261),IF(A4=MATCH(TRUE,$Y$2:$Y$261,0)-1,0,NA())) | AE4: =IF(A4=MATCH(TRUE,$Z$2:$Z$261,0),MAX($AB$2:$AB$261),IF(A4=MATCH(TRUE,$Z$2:$Z$261,0)-1,0,NA()))
A5: 4 | B5: =Variables!$B$24+(A5-1)*7 | C5: =P4 | D5: =Q4 | E5: =C5+IF(A5>Variables!$B$25,D5,0) | F5: =C5+D5 | G5: =IF(A5>Variables!$B$22,Variables!$B$12,0) | H5: =IF(AND(A5>Variables!$B$22,Variables!$B$14="Yes"),Variables!$B$13,0) | I5: =IF(AA5>Variables!$B$18,0,IF(AA5>Variables!$B$19,CEILING((AA5-Variables!$B$19)/Variables!$B$21,1)*Variables!$B$20,0)) | J5: =IF(AA5<=Variables!$B$18,MIN(Variables!$B$9-Variables!$B$8+I5,Variables!$B$26),0) | K5: =IF(AA5<=Variables!$B$18,Variables!$B$27,0) | L5: =IF(AA5>Variables!$B$18,G5+H5,Variables!$B$26-J5) | M5: =IF(AA5>Variables!$B$18,Variables!$B$2-G5-H5,J5+K5) | N5: =Variables!$B$9-AC5 | O5: =F5+N5 | P5: =MAX(0,C5+N5) | Q5: =D5+MIN(0,C5+N5) | R5: =IF(AA5>Variables!$B$18,"Self-funder",IF(AA5>Variables!$B$19,"Tariff band - council contributing","Council pays standard rate")) | S5: =Variables!$B$18 | T5: =Variables!$B$19 | U5: =AA5<=Variables!$B$18 | V5: =AA5<=Variables!$B$19 | W5: =P5<=0 | X5: =Variables!$B$28 | Y5: =AB5<=Variables!$B$28 | Z5: =AB5<=Variables!$B$18 | AA5: =AB4 | AB5: =AA5+Variables!$B$9-M5 | AC5: =IF(MOD(A5-1,Variables!$B$30)=0,Variables!$B$30*M5,0) | AD5: =IF(A5=MATCH(TRUE,$Y$2:$Y$261,0),MAX($AB$2:$AB$261),IF(A5=MATCH(TRUE,$Y$2:$Y$261,0)-1,0,NA())) | AE5: =IF(A5=MATCH(TRUE,$Z$2:$Z$261,0),MAX($AB$2:$AB$261),IF(A5=MATCH(TRUE,$Z$2:$Z$261,0)-1,0,NA()))
A6: 5 | B6: =Variables!$B$24+(A6-1)*7 | C6: =P5 | D6: =Q5 | E6: =C6+IF(A6>Variables!$B$25,D6,0) | F6: =C6+D6 | G6: =IF(A6>Variables!$B$22,Variables!$B$12,0) | H6: =IF(AND(A6>Variables!$B$22,Variables!$B$14="Yes"),Variables!$B$13,0) | I6: =IF(AA6>Variables!$B$18,0,IF(AA6>Variables!$B$19,CEILING((AA6-Variables!$B$19)/Variables!$B$21,1)*Variables!$B$20,0)) | J6: =IF(AA6<=Variables!$B$18,MIN(Variables!$B$9-Variables!$B$8+I6,Variables!$B$26),0) | K6: =IF(AA6<=Variables!$B$18,Variables!$B$27,0) | L6: =IF(AA6>Variables!$B$18,G6+H6,Variables!$B$26-J6) | M6: =IF(AA6>Variables!$B$18,Variables!$B$2-G6-H6,J6+K6) | N6: =Variables!$B$9-AC6 | O6: =F6+N6 | P6: =MAX(0,C6+N6) | Q6: =D6+MIN(0,C6+N6) | R6: =IF(AA6>Variables!$B$18,"Self-funder",IF(AA6>Variables!$B$19,"Tariff band - council contributing","Council pays standard rate")) | S6: =Variables!$B$18 | T6: =Variables!$B$19 | U6: =AA6<=Variables!$B$18 | V6: =AA6<=Variables!$B$19 | W6: =P6<=0 | X6: =Variables!$B$28 | Y6: =AB6<=Variables!$B$28 | Z6: =AB6<=Variables!$B$18 | AA6: =AB5 | AB6: =AA6+Variables!$B$9-M6 | AC6: =IF(MOD(A6-1,Variables!$B$30)=0,Variables!$B$30*M6,0) | AD6: =IF(A6=MATCH(TRUE,$Y$2:$Y$261,0),MAX($AB$2:$AB$261),IF(A6=MATCH(TRUE,$Y$2:$Y$261,0)-1,0,NA())) | AE6: =IF(A6=MATCH(TRUE,$Z$2:$Z$261,0),MAX($AB$2:$AB$261),IF(A6=MATCH(TRUE,$Z$2:$Z$261,0)-1,0,NA()))
A7: 6 | B7: =Variables!$B$24+(A7-1)*7 | C7: =P6 | D7: =Q6 | E7: =C7+IF(A7>Variables!$B$25,D7,0) | F7: =C7+D7 | G7: =IF(A7>Variables!$B$22,Variables!$B$12,0) | H7: =IF(AND(A7>Variables!$B$22,Variables!$B$14="Yes"),Variables!$B$13,0) | I7: =IF(AA7>Variables!$B$18,0,IF(AA7>Variables!$B$19,CEILING((AA7-Variables!$B$19)/Variables!$B$21,1)*Variables!$B$20,0)) | J7: =IF(AA7<=Variables!$B$18,MIN(Variables!$B$9-Variables!$B$8+I7,Variables!$B$26),0) | K7: =IF(AA7<=Variables!$B$18,Variables!$B$27,0) | L7: =IF(AA7>Variables!$B$18,G7+H7,Variables!$B$26-J7) | M7: =IF(AA7>Variables!$B$18,Variables!$B$2-G7-H7,J7+K7) | N7: =Variables!$B$9-AC7 | O7: =F7+N7 | P7: =MAX(0,C7+N7) | Q7: =D7+MIN(0,C7+N7) | R7: =IF(AA7>Variables!$B$18,"Self-funder",IF(AA7>Variables!$B$19,"Tariff band - council contributing","Council pays standard rate")) | S7: =Variables!$B$18 | T7: =Variables!$B$19 | U7: =AA7<=Variables!$B$18 | V7: =AA7<=Variables!$B$19 | W7: =P7<=0 | X7: =Variables!$B$28 | Y7: =AB7<=Variables!$B$28 | Z7: =AB7<=Variables!$B$18 | AA7: =AB6 | AB7: =AA7+Variables!$B$9-M7 | AC7: =IF(MOD(A7-1,Variables!$B$30)=0,Variables!$B$30*M7,0) | AD7: =IF(A7=MATCH(TRUE,$Y$2:$Y$261,0),MAX($AB$2:$AB$261),IF(A7=MATCH(TRUE,$Y$2:$Y$261,0)-1,0,NA())) | AE7: =IF(A7=MATCH(TRUE,$Z$2:$Z$261,0),MAX($AB$2:$AB$261),IF(A7=MATCH(TRUE,$Z$2:$Z$261,0)-1,0,NA()))
A8: 7 | B8: =Variables!$B$24+(A8-1)*7 | C8: =P7 | D8: =Q7 | E8: =C8+IF(A8>Variables!$B$25,D8,0) | F8: =C8+D8 | G8: =IF(A8>Variables!$B$22,Variables!$B$12,0) | H8: =IF(AND(A8>Variables!$B$22,Variables!$B$14="Yes"),Variables!$B$13,0) | I8: =IF(AA8>Variables!$B$18,0,IF(AA8>Variables!$B$19,CEILING((AA8-Variables!$B$19)/Variables!$B$21,1)*Variables!$B$20,0)) | J8: =IF(AA8<=Variables!$B$18,MIN(Variables!$B$9-Variables!$B$8+I8,Variables!$B$26),0) | K8: =IF(AA8<=Variables!$B$18,Variables!$B$27,0) | L8: =IF(AA8>Variables!$B$18,G8+H8,Variables!$B$26-J8) | M8: =IF(AA8>Variables!$B$18,Variables!$B$2-G8-H8,J8+K8) | N8: =Variables!$B$9-AC8 | O8: =F8+N8 | P8: =MAX(0,C8+N8) | Q8: =D8+MIN(0,C8+N8) | R8: =IF(AA8>Variables!$B$18,"Self-funder",IF(AA8>Variables!$B$19,"Tariff band - council contributing","Council pays standard rate")) | S8: =Variables!$B$18 | T8: =Variables!$B$19 | U8: =AA8<=Variables!$B$18 | V8: =AA8<=Variables!$B$19 | W8: =P8<=0 | X8: =Variables!$B$28 | Y8: =AB8<=Variables!$B$28 | Z8: =AB8<=Variables!$B$18 | AA8: =AB7 | AB8: =AA8+Variables!$B$9-M8 | AC8: =IF(MOD(A8-1,Variables!$B$30)=0,Variables!$B$30*M8,0) | AD8: =IF(A8=MATCH(TRUE,$Y$2:$Y$261,0),MAX($AB$2:$AB$261),IF(A8=MATCH(TRUE,$Y$2:$Y$261,0)-1,0,NA())) | AE8: =IF(A8=MATCH(TRUE,$Z$2:$Z$261,0),MAX($AB$2:$AB$261),IF(A8=MATCH(TRUE,$Z$2:$Z$261,0)-1,0,NA()))
A9: 8 | B9: =Variables!$B$24+(A9-1)*7 | C9: =P8 | D9: =Q8 | E9: =C9+IF(A9>Variables!$B$25,D9,0) | F9: =C9+D9 | G9: =IF(A9>Variables!$B$22,Variables!$B$12,0) | H9: =IF(AND(A9>Variables!$B$22,Variables!$B$14="Yes"),Variables!$B$13,0) | I9: =IF(AA9>Variables!$B$18,0,IF(AA9>Variables!$B$19,CEILING((AA9-Variables!$B$19)/Variables!$B$21,1)*Variables!$B$20,0)) | J9: =IF(AA9<=Variables!$B$18,MIN(Variables!$B$9-Variables!$B$8+I9,Variables!$B$26),0) | K9: =IF(AA9<=Variables!$B$18,Variables!$B$27,0) | L9: =IF(AA9>Variables!$B$18,G9+H9,Variables!$B$26-J9) | M9: =IF(AA9>Variables!$B$18,Variables!$B$2-G9-H9,J9+K9) | N9: =Variables!$B$9-AC9 | O9: =F9+N9 | P9: =MAX(0,C9+N9) | Q9: =D9+MIN(0,C9+N9) | R9: =IF(AA9>Variables!$B$18,"Self-funder",IF(AA9>Variables!$B$19,"Tariff band - council contributing","Council pays standard rate")) | S9: =Variables!$B$18 | T9: =Variables!$B$19 | U9: =AA9<=Variables!$B$18 | V9: =AA9<=Variables!$B$19 | W9: =P9<=0 | X9: =Variables!$B$28 | Y9: =AB9<=Variables!$B$28 | Z9: =AB9<=Variables!$B$18 | AA9: =AB8 | AB9: =AA9+Variables!$B$9-M9 | AC9: =IF(MOD(A9-1,Variables!$B$30)=0,Variables!$B$30*M9,0) | AD9: =IF(A9=MATCH(TRUE,$Y$2:$Y$261,0),MAX($AB$2:$AB$261),IF(A9=MATCH(TRUE,$Y$2:$Y$261,0)-1,0,NA())) | AE9: =IF(A9=MATCH(TRUE,$Z$2:$Z$261,0),MAX($AB$2:$AB$261),IF(A9=MATCH(TRUE,$Z$2:$Z$261,0)-1,0,NA()))
A10: 9 | B10: =Variables!$B$24+(A10-1)*7 | C10: =P9 | D10: =Q9 | E10: =C10+IF(A10>Variables!$B$25,D10,0) | F10: =C10+D10 | G10: =IF(A10>Variables!$B$22,Variables!$B$12,0) | H10: =IF(AND(A10>Variables!$B$22,Variables!$B$14="Yes"),Variables!$B$13,0) | I10: =IF(AA10>Variables!$B$18,0,IF(AA10>Variables!$B$19,CEILING((AA10-Variables!$B$19)/Variables!$B$21,1)*Variables!$B$20,0)) | J10: =IF(AA10<=Variables!$B$18,MIN(Variables!$B$9-Variables!$B$8+I10,Variables!$B$26),0) | K10: =IF(AA10<=Variables!$B$18,Variables!$B$27,0) | L10: =IF(AA10>Variables!$B$18,G10+H10,Variables!$B$26-J10) | M10: =IF(AA10>Variables!$B$18,Variables!$B$2-G10-H10,J10+K10) | N10: =Variables!$B$9-AC10 | O10: =F10+N10 | P10: =MAX(0,C10+N10) | Q10: =D10+MIN(0,C10+N10) | R10: =IF(AA10>Variables!$B$18,"Self-funder",IF(AA10>Variables!$B$19,"Tariff band - council contributing","Council pays standard rate")) | S10: =Variables!$B$18 | T10: =Variables!$B$19 | U10: =AA10<=Variables!$B$18 | V10: =AA10<=Variables!$B$19 | W10: =P10<=0 | X10: =Variables!$B$28 | Y10: =AB10<=Variables!$B$28 | Z10: =AB10<=Variables!$B$18 | AA10: =AB9 | AB10: =AA10+Variables!$B$9-M10 | AC10: =IF(MOD(A10-1,Variables!$B$30)=0,Variables!$B$30*M10,0) | AD10: =IF(A10=MATCH(TRUE,$Y$2:$Y$261,0),MAX($AB$2:$AB$261),IF(A10=MATCH(TRUE,$Y$2:$Y$261,0)-1,0,NA())) | AE10: =IF(A10=MATCH(TRUE,$Z$2:$Z$261,0),MAX($AB$2:$AB$261),IF(A10=MATCH(TRUE,$Z$2:$Z$261,0)-1,0,NA()))
A11: 10 | B11: =Variables!$B$24+(A11-1)*7 | C11: =P10 | D11: =Q10 | E11: =C11+IF(A11>Variables!$B$25,D11,0) | F11: =C11+D11 | G11: =IF(A11>Variables!$B$22,Variables!$B$12,0) | H11: =IF(AND(A11>Variables!$B$22,Variables!$B$14="Yes"),Variables!$B$13,0) | I11: =IF(AA11>Variables!$B$18,0,IF(AA11>Variables!$B$19,CEILING((AA11-Variables!$B$19)/Variables!$B$21,1)*Variables!$B$20,0)) | J11: =IF(AA11<=Variables!$B$18,MIN(Variables!$B$9-Variables!$B$8+I11,Variables!$B$26),0) | K11: =IF(AA11<=Variables!$B$18,Variables!$B$27,0) | L11: =IF(AA11>Variables!$B$18,G11+H11,Variables!$B$26-J11) | M11: =IF(AA11>Variables!$B$18,Variables!$B$2-G11-H11,J11+K11) | N11: =Variables!$B$9-AC11 | O11: =F11+N11 | P11: =MAX(0,C11+N11) | Q11: =D11+MIN(0,C11+N11) | R11: =IF(AA11>Variables!$B$18,"Self-funder",IF(AA11>Variables!$B$19,"Tariff band - council contributing","Council pays standard rate")) | S11: =Variables!$B$18 | T11: =Variables!$B$19 | U11: =AA11<=Variables!$B$18 | V11: =AA11<=Variables!$B$19 | W11: =P11<=0 | X11: =Variables!$B$28 | Y11: =AB11<=Variables!$B$28 | Z11: =AB11<=Variables!$B$18 | AA11: =AB10 | AB11: =AA11+Variables!$B$9-M11 | AC11: =IF(MOD(A11-1,Variables!$B$30)=0,Variables!$B$30*M11,0) | AD11: =IF(A11=MATCH(TRUE,$Y$2:$Y$261,0),MAX($AB$2:$AB$261),IF(A11=MATCH(TRUE,$Y$2:$Y$261,0)-1,0,NA())) | AE11: =IF(A11=MATCH(TRUE,$Z$2:$Z$261,0),MAX($AB$2:$AB$261),IF(A11=MATCH(TRUE,$Z$2:$Z$261,0)-1,0,NA()))
A12: 11 | B12: =Variables!$B$24+(A12-1)*7 | C12: =P11 | D12: =Q11 | E12: =C12+IF(A12>Variables!$B$25,D12,0) | F12: =C12+D12 | G12: =IF(A12>Variables!$B$22,Variables!$B$12,0) | H12: =IF(AND(A12>Variables!$B$22,Variables!$B$14="Yes"),Variables!$B$13,0) | I12: =IF(AA12>Variables!$B$18,0,IF(AA12>Variables!$B$19,CEILING((AA12-Variables!$B$19)/Variables!$B$21,1)*Variables!$B$20,0)) | J12: =IF(AA12<=Variables!$B$18,MIN(Variables!$B$9-Variables!$B$8+I12,Variables!$B$26),0) | K12: =IF(AA12<=Variables!$B$18,Variables!$B$27,0) | L12: =IF(AA12>Variables!$B$18,G12+H12,Variables!$B$26-J12) | M12: =IF(AA12>Variables!$B$18,Variables!$B$2-G12-H12,J12+K12) | N12: =Variables!$B$9-AC12 | O12: =F12+N12 | P12: =MAX(0,C12+N12) | Q12: =D12+MIN(0,C12+N12) | R12: =IF(AA12>Variables!$B$18,"Self-funder",IF(AA12>Variables!$B$19,"Tariff band - council contributing","Council pays standard rate")) | S12: =Variables!$B$18 | T12: =Variables!$B$19 | U12: =AA12<=Variables!$B$18 | V12: =AA12<=Variables!$B$19 | W12: =P12<=0 | X12: =Variables!$B$28 | Y12: =AB12<=Variables!$B$28 | Z12: =AB12<=Variables!$B$18 | AA12: =AB11 | AB12: =AA12+Variables!$B$9-M12 | AC12: =IF(MOD(A12-1,Variables!$B$30)=0,Variables!$B$30*M12,0) | AD12: =IF(A12=MATCH(TRUE,$Y$2:$Y$261,0),MAX($AB$2:$AB$261),IF(A12=MATCH(TRUE,$Y$2:$Y$261,0)-1,0,NA())) | AE12: =IF(A12=MATCH(TRUE,$Z$2:$Z$261,0),MAX($AB$2:$AB$261),IF(A12=MATCH(TRUE,$Z$2:$Z$261,0)-1,0,NA()))
A13: 12 | B13: =Variables!$B$24+(A13-1)*7 | C13: =P12 | D13: =Q12 | E13: =C13+IF(A13>Variables!$B$25,D13,0) | F13: =C13+D13 | G13: =IF(A13>Variables!$B$22,Variables!$B$12,0) | H13: =IF(AND(A13>Variables!$B$22,Variables!$B$14="Yes"),Variables!$B$13,0) | I13: =IF(AA13>Variables!$B$18,0,IF(AA13>Variables!$B$19,CEILING((AA13-Variables!$B$19)/Variables!$B$21,1)*Variables!$B$20,0)) | J13: =IF(AA13<=Variables!$B$18,MIN(Variables!$B$9-Variables!$B$8+I13,Variables!$B$26),0) | K13: =IF(AA13<=Variables!$B$18,Variables!$B$27,0) | L13: =IF(AA13>Variables!$B$18,G13+H13,Variables!$B$26-J13) | M13: =IF(AA13>Variables!$B$18,Variables!$B$2-G13-H13,J13+K13) | N13: =Variables!$B$9-AC13 | O13: =F13+N13 | P13: =MAX(0,C13+N13) | Q13: =D13+MIN(0,C13+N13) | R13: =IF(AA13>Variables!$B$18,"Self-funder",IF(AA13>Variables!$B$19,"Tariff band - council contributing","Council pays standard rate")) | S13: =Variables!$B$18 | T13: =Variables!$B$19 | U13: =AA13<=Variables!$B$18 | V13: =AA13<=Variables!$B$19 | W13: =P13<=0 | X13: =Variables!$B$28 | Y13: =AB13<=Variables!$B$28 | Z13: =AB13<=Variables!$B$18 | AA13: =AB12 | AB13: =AA13+Variables!$B$9-M13 | AC13: =IF(MOD(A13-1,Variables!$B$30)=0,Variables!$B$30*M13,0) | AD13: =IF(A13=MATCH(TRUE,$Y$2:$Y$261,0),MAX($AB$2:$AB$261),IF(A13=MATCH(TRUE,$Y$2:$Y$261,0)-1,0,NA())) | AE13: =IF(A13=MATCH(TRUE,$Z$2:$Z$261,0),MAX($AB$2:$AB$261),IF(A13=MATCH(TRUE,$Z$2:$Z$261,0)-1,0,NA()))
A14: 13 | B14: =Variables!$B$24+(A14-1)*7 | C14: =P13 | D14: =Q13 | E14: =C14+IF(A14>Variables!$B$25,D14,0) | F14: =C14+D14 | G14: =IF(A14>Variables!$B$22,Variables!$B$12,0) | H14: =IF(AND(A14>Variables!$B$22,Variables!$B$14="Yes"),Variables!$B$13,0) | I14: =IF(AA14>Variables!$B$18,0,IF(AA14>Variables!$B$19,CEILING((AA14-Variables!$B$19)/Variables!$B$21,1)*Variables!$B$20,0)) | J14: =IF(AA14<=Variables!$B$18,MIN(Variables!$B$9-Variables!$B$8+I14,Variables!$B$26),0) | K14: =IF(AA14<=Variables!$B$18,Variables!$B$27,0) | L14: =IF(AA14>Variables!$B$18,G14+H14,Variables!$B$26-J14) | M14: =IF(AA14>Variables!$B$18,Variables!$B$2-G14-H14,J14+K14) | N14: =Variables!$B$9-AC14 | O14: =F14+N14 | P14: =MAX(0,C14+N14) | Q14: =D14+MIN(0,C14+N14) | R14: =IF(AA14>Variables!$B$18,"Self-funder",IF(AA14>Variables!$B$19,"Tariff band - council contributing","Council pays standard rate")) | S14: =Variables!$B$18 | T14: =Variables!$B$19 | U14: =AA14<=Variables!$B$18 | V14: =AA14<=Variables!$B$19 | W14: =P14<=0 | X14: =Variables!$B$28 | Y14: =AB14<=Variables!$B$28 | Z14: =AB14<=Variables!$B$18 | AA14: =AB13 | AB14: =AA14+Variables!$B$9-M14 | AC14: =IF(MOD(A14-1,Variables!$B$30)=0,Variables!$B$30*M14,0) | AD14: =IF(A14=MATCH(TRUE,$Y$2:$Y$261,0),MAX($AB$2:$AB$261),IF(A14=MATCH(TRUE,$Y$2:$Y$261,0)-1,0,NA())) | AE14: =IF(A14=MATCH(TRUE,$Z$2:$Z$261,0),MAX($AB$2:$AB$261),IF(A14=MATCH(TRUE,$Z$2:$Z$261,0)-1,0,NA()))
... A261: 260 | B261: =Variables!$B$24+(A261-1)*7 | C261: =P260 | D261: =Q260 | E261: =C261+IF(A261>Variables!$B$25,D261,0) | F261: =C261+D261 | G261: =IF(A261>Variables!$B$22,Variables!$B$12,0) | H261: =IF(AND(A261>Variables!$B$22,Variables!$B$14="Yes"),Variables!$B$13,0) | I261: =IF(AA261>Variables!$B$18,0,IF(AA261>Variables!$B$19,CEILING((AA261-Variables!$B$19)/Variables!$B$21,1)*Variables!$B$20,0)) | J261: =IF(AA261<=Variables!$B$18,MIN(Variables!$B$9-Variables!$B$8+I261,Variables!$B$26),0) | K261: =IF(AA261<=Variables!$B$18,Variables!$B$27,0) | L261: =IF(AA261>Variables!$B$18,G261+H261,Variables!$B$26-J261) | M261: =IF(AA261>Variables!$B$18,Variables!$B$2-G261-H261,J261+K261) | N261: =Variables!$B$9-AC261 | O261: =F261+N261 | P261: =MAX(0,C261+N261) | Q261: =D261+MIN(0,C261+N261) | R261: =IF(AA261>Variables!$B$18,"Self-funder",IF(AA261>Variables!$B$19,"Tariff band - council contributing","Council pays standard rate")) | S261: =Variables!$B$18 | T261: =Variables!$B$19 | U261: =AA261<=Variables!$B$18 | V261: =AA261<=Variables!$B$19 | W261: =P261<=0 | X261: =Variables!$B$28 | Y261: =AB261<=Variables!$B$28 | Z261: =AB261<=Variables!$B$18 | AA261: =AB260 | AB261: =AA261+Variables!$B$9-M261 | AC261: =IF(MOD(A261-1,Variables!$B$30)=0,Variables!$B$30*M261,0) | AD261: =IF(A261=MATCH(TRUE,$Y$2:$Y$261,0),MAX($AB$2:$AB$261),IF(A261=MATCH(TRUE,$Y$2:$Y$261,0)-1,0,NA())) | AE261: =IF(A261=MATCH(TRUE,$Z$2:$Z$261,0),MAX($AB$2:$AB$261),IF(A261=MATCH(TRUE,$Z$2:$Z$261,0)-1,0,NA()))

Sheet Notes
A1: How this model works (Scotland)
A3: 1. FUNDING STATUS uses TOTAL wealth = cash + home value.
A4: - Total wealth above the UPPER limit -> self-funder.
A5: - Total wealth at or below it -> council contributes up to the standard rate.
A6: The 'Assessed capital' column also shows the 12-week property disregard (home
A7: excluded for the first N weeks); it is informational for self-funders.
A9: 2. FREE PERSONAL / NURSING CARE are not means-tested.
A10: The council pays FPC (and FNC if nursing is awarded) to the care home regardless of capital.
A11: So a self-funder pays: fee - FPC - FNC.
A12: FPC/FNC are awarded N weeks after entering care (set on the Variables sheet).
A14: 3. NO DOUBLE COUNTING: the NCHC standard rate already includes FPC and FNC.
A15: When council-funded the council pays: standard rate - assessed contribution.
... A51: - A real local-authority financial assessment may vary; treat this as a planning model.
